Workbook

Sheet 1_Inputs
A1: Air Quality Engineering Alternatives Tool — User Inputs
A2: Blue cells are user-adjustable inputs. All other cells are calculated. Do not edit gray or black cells.
B3: Parameter | C3: Value | D3: Units | E3: Source | F3: Notes
B4: SOURCE CHARACTERISTICS
B5: Emission rate (Q) | C5: 50 | D5: g/s | E5: EPA AP-42 | F5: Mass of PM2.5 emitted per second
B6: Stack height (H) | C6: 30 | D6: m | E6: Site data | F6: Effective release height
B7: Stack exit velocity | C7: 12 | D7: m/s | E7: Site data | F7: Flue gas exit speed
B8: Stack diameter | C8: 1.5 | D8: m | E8: Site data | F8: Inner diameter of stack
B9: METEOROLOGICAL CONDITIONS
B10: Mean wind speed (u) | C10: 3.5 | D10: m/s | E10: NWS Fort Collins | F10: Annual average at hub height
B11: Pasquill stability class (1–6) | C11: 3 | D11: — | E11: EPA guidance | F11: 1=A(unstable)…6=F(stable). 3=C
B12: Wind direction (for display) | C12: 270 | D12: degrees | E12: NWS | F12: Prevailing wind bearing
B13: RECEPTOR / SITE GEOMETRY
B14: Source–receptor distance (x) | C14: 500 | D14: m | E14: GIS measurement | F14: Center of residential area
B15: Receptor height (z) | C15: 1.5 | D15: m | E15: Standard | F15: Breathing height
B16: Lateral offset (y) | C16: 0 | D16: m | E16: Worst-case | F16: Centerline = maximum impact
B17: ALTERNATIVE A — COMMUNITY VEGETATION BUFFER
B18: Buffer width | C18: 20 | D18: m | E18: Design spec | F18: Width of planted barrier
B19: Vegetation reduction factor | C19: 0.25 | D19: fraction | E19: Literature | F19: Fraction of C_out removed (10–40%)
B20: Buffer capital cost | C20: 180000 | D20: USD | E20: Estimate | F20: Installed cost for 300 m linear buffer
B21: Buffer annual O&M | C21: 8000 | D21: USD/yr | E21: Estimate | F21: Irrigation, replacement planting
B22: ALTERNATIVE B — HOME HEPA FILTRATION + SEALING
B23: Number of homes treated | C23: 120 | D23: homes | E23: Census block | F23: Homes in receptor area
B24: HEPA filter efficiency | C24: 0.85 | D24: fraction | E24: ASHRAE | F24: Fraction of indoor PM2.5 removed
B25: Infiltration rate (ACH_nat) | C25: 0.45 | D25: 1/hr | E25: ASHRAE | F25: Natural air changes per hour
B26: Mechanical ventilation rate (ACH_mech) | C26: 0.15 | D26: 1/hr | E26: Design | F26: Added ventilation from ERV/HRV
B27: Cost per home (install) | C27: 1800 | D27: USD/home | E27: RSMeans | F27: HEPA + sealing labor + materials
B28: Annual filter replacement / home | C28: 120 | D28: USD/yr/home | E28: Vendor | F28: Filter cartridge replacement
B29: Average occupant time indoors | C29: 16 | D29: hr/day | E29: EPA CHAD | F29: Time spent inside residence
B30: MCDA WEIGHTS (used on MCDA tab)
B31: Weight — Technical Effectiveness | C31: 0.35 | D31: fraction | E31: User-set | F31: Must sum to 1.0 across four criteria
B32: Weight — Cost & Practicality | C32: 0.25 | D32: fraction | E32: User-set
B33: Weight — Public Health & Safety | C33: 0.25 | D33: fraction | E33: User-set
B34: Weight — Environmental | C34: 0.15 | D34: fraction | E34: User-set
B35: ↳ Weights sum (must = 1.0) | C35: =C31+C32+C33+C34 -> 1

Sheet 2_Model
A1: Air Quality Model — Gaussian Dispersion + Single-Zone Indoor
B2: Parameter / Step | C2: Baseline | D2: Alt A (Buffer) | E2: Alt B (HEPA) | F2: Formula / Notes
B3: STEP 1 — GAUSSIAN PLUME DISPERSION (outdoor C at receptor)
B4: Stability class (from Inputs) | C4: ='1_Inputs'!C11 -> 3 | D4: ='1_Inputs'!C11 -> 3 | E4: ='1_Inputs'!C11 -> 3 | F4: Pulled from Inputs tab
B5: Wind speed u (m/s) | C5: ='1_Inputs'!C10 -> 3.5 | D5: ='1_Inputs'!C10 -> 3.5 | E5: ='1_Inputs'!C10 -> 3.5 | F5: Pulled from Inputs
B6: Emission rate Q (g/s) | C6: ='1_Inputs'!C5 -> 50 | D6: ='1_Inputs'!C5 -> 50 | E6: ='1_Inputs'!C5 -> 50 | F6: Same source for all scenarios
B7: Effective stack height H (m) | C7: ='1_Inputs'!C6 -> 30 | D7: ='1_Inputs'!C6 -> 30 | E7: ='1_Inputs'!C6 -> 30 | F7: Stack height (m)
B8: Source–receptor distance x (m) | C8: ='1_Inputs'!C14 -> 500 | D8: ='1_Inputs'!C14 -> 500 | E8: ='1_Inputs'!C14 -> 500
B9: x in km (for σ equations) | C9: =C8/1000 -> 0.5 | D9: =D8/1000 -> 0.5 | E9: =E8/1000 -> 0.5 | F9: Convert m to km
B10: σy dispersion coeff (m) | C10: =156*(C9^0.922) -> 82.33319 | D10: =156*(D9^0.922) -> 82.33319 | E10: =156*(E9^0.922) -> 82.33319 | F10: P-G class C: σy=156·x^0.922
B11: σz dispersion coeff (m) | C11: =108.2*(C9^0.816) -> 61.459183 | D11: =108.2*(D9^0.816) -> 61.459183 | E11: =108.2*(E9^0.816) -> 61.459183 | F11: P-G class C: σz=108·x^0.816
B12: Outdoor ground-level C_out (µg/m³) | C12: =((C6*1000000)/(3.14159*C10*C11*C5))*EXP(-(C7^2)/(2*C11^2)) -> 797.72115 | D12: =((D6*1000000)/(3.14159*D10*D11*D5))*EXP(-(D7^2)/(2*D11^2)) -> 797.72115 | E12: =((E6*1000000)/(3.14159*E10*E11*E5))*EXP(-(E7^2)/(2*E11^2)) -> 797.72115 | F12: Gaussian plume (centerline, z=0): C=Q/(π·σy·σz·u)·e^(-H²/2σz²)
B14: STEP 2 — ALTERNATIVE A: VEGETATION BUFFER EFFECT ON C_out
B15: Vegetation reduction factor (f_buf) | C15: =0 -> 0 | D15: ='1_Inputs'!C19 -> 0.25 | E15: =0 -> 0 | F15: Fraction of C_out removed by buffer (Alt A only)
B16: C_out after buffer (µg/m³) | C16: =C12 -> 797.72115 | D16: =D12*(1-D15) -> 598.29086 | E16: =E12*(1-E15) -> 797.72115 | F16: Baseline unchanged; Alt A applies buffer reduction
B18: STEP 3 — SINGLE-ZONE INDOOR MODEL (mass balance)
B19: Natural infiltration rate ACH_nat (1/hr) | C19: ='1_Inputs'!C25 -> 0.45 | D19: ='1_Inputs'!C25 -> 0.45 | E19: ='1_Inputs'!C25 -> 0.45
B20: Mechanical ventilation ACH_mech (1/hr) | C20: =0 -> 0 | D20: =0 -> 0 | E20: ='1_Inputs'!C26 -> 0.15 | F20: Alt B adds mechanical ERV/HRV
B21: HEPA filter efficiency (η) | C21: =0 -> 0 | D21: =0 -> 0 | E21: ='1_Inputs'!C24 -> 0.85 | F21: Only Alt B applies filtration
B22: Effective removal rate from filtration (1/hr) | C22: =C19*C21 -> 0 | D22: =D19*D21 -> 0 | E22: =(E19+E20)*E21 -> 0.51 | F22: Removal rate = (ACH_nat+ACH_mech) × η for Alt B
B23: Total air exchange + removal (1/hr) | C23: =C19+C20+C22 -> 0.45 | D23: =D19+D20+D22 -> 0.45 | E23: =E19+E20+E22 -> 1.11 | F23: Denominator of single-zone steady-state equation
B24: Indoor steady-state C_in (µg/m³) | C24: =IF(C23>0,C16*(C19/C23),0) -> 797.72115 | D24: =IF(D23>0,D16*(D19/D23),0) -> 598.29086 | E24: =IF(E23>0,E16*(E19/E23),0) -> 323.40046 | F24: C_in = C_out_adj × ACH_nat / (total exchange + removal)
B26: STEP 4 — OCCUPANT DOSE
B27: Time indoors (hr/day) | C27: ='1_Inputs'!C29 -> 16 | D27: ='1_Inputs'!C29 -> 16 | E27: ='1_Inputs'!C29 -> 16
B28: Daily inhalation volume (m³/day) | C28: =24*0.5*0.012 -> 0.144 | D28: =24*0.5*0.012 -> 0.144 | E28: =24*0.5*0.012 -> 0.144 | F28: ~0.144 m³/day (0.5 m³/hr at rest, 12 hr)
B29: Daily dose indoors (µg/day) | C29: =C24*C27*C28 -> 1837.9495 | D29: =D24*D27*D28 -> 1378.4621 | E29: =E24*E27*E28 -> 745.11467 | F29: Dose = C_in × time × inhalation rate
B31: STEP 5 — DOSE REDUCTION vs. BASELINE
B32: Absolute dose reduction (µg/day) | C32: =0 -> 0 | D32: =C29-D29 -> 459.48738 | E32: =C29-E29 -> 1092.8349 | F32: Baseline dose minus alternative dose
B33: Percent dose reduction (%) | C33: =0 -> 0 | D33: =IF(C29>0,(C29-D29)/C29*100,0) -> 25 | E33: =IF(C29>0,(C29-E29)/C29*100,0) -> 59.459459 | F33: % improvement vs. baseline
B35: STEP 6 — COST SUMMARY
B36: Capital cost (USD) | C36: =0 -> 0 | D36: ='1_Inputs'!C20 -> 180000 | E36: ='1_Inputs'!C27*'1_Inputs'!C23 -> 216000 | F36: Alt A: buffer install; Alt B: cost/home × homes
B37: Annual O&M cost (USD/yr) | C37: =0 -> 0 | D37: ='1_Inputs'!C21 -> 8000 | E37: ='1_Inputs'!C28*'1_Inputs'!C23 -> 14400 | F37: Alt A: maintenance; Alt B: filter replacement × homes
B38: 20-year lifecycle cost (USD) | C38: =0 -> 0 | D38: =IF(D36>0,D36+20*D37,0) -> 340000 | E38: =IF(E36>0,E36+20*E37,0) -> 504000 | F38: Capital + 20 years O&M (undiscounted)

Sheet 3_Results
A1: Results Dashboard — Comparison of Engineering Alternatives
B2: Metric | C2: Baseline (no action) | D2: Alt A — Community Buffer | E2: Alt B — Home Filtration | F2: Notes
B3: AIR QUALITY MODEL OUTPUTS
B4: Outdoor C_out — baseline (µg/m³) | C4: ='2_Model'!C12 -> 797.72115 | D4: — | E4: — | F4: Gaussian plume at receptor
B5: Outdoor C_out after intervention (µg/m³) | C5: ='2_Model'!C16 -> 797.72115 | D5: ='2_Model'!D16 -> 598.29086 | E5: ='2_Model'!E16 -> 797.72115 | F5: Alt A reduces C_out; Alt B unchanged
B6: Indoor steady-state C_in (µg/m³) | C6: ='2_Model'!C24 -> 797.72115 | D6: ='2_Model'!D24 -> 598.29086 | E6: ='2_Model'!E24 -> 323.40046 | F6: Single-zone mass balance
B7: Daily occupant dose (µg/day) | C7: ='2_Model'!C29 -> 1837.9495 | D7: ='2_Model'!D29 -> 1378.4621 | E7: ='2_Model'!E29 -> 745.11467 | F7: C_in × time × inhalation
B8: Dose reduction vs. baseline (%) | C8: — | D8: ='2_Model'!D33 -> 25 | E8: ='2_Model'!E33 -> 59.459459 | F8: Percent improvement
B9: COST SUMMARY
B10: Capital cost (USD) | C10: — | D10: ='2_Model'!D36 -> 180000 | E10: ='2_Model'!E36 -> 216000
B11: Annual O&M cost (USD/yr) | C11: — | D11: ='2_Model'!D37 -> 8000 | E11: ='2_Model'!E37 -> 14400
B12: 20-year lifecycle cost (USD) | C12: — | D12: ='2_Model'!D38 -> 340000 | E12: ='2_Model'!E38 -> 504000 | F12: Undiscounted
B13: Cost per % dose reduction (USD) | C13: — | D13: =IF('2_Model'!D33>0,'2_Model'!D38/'2_Model'!D33,"N/A") -> 13600 | E13: =IF('2_Model'!E33>0,'2_Model'!E38/'2_Model'!E33,"N/A") -> 8476.3636 | F13: Lifecycle cost ÷ % dose reduction
B14: WEIGHTED MCDA SCORE (from MCDA tab)
B15: Overall MCDA weighted score | C15: — | D15: ='4_MCDA'!C31 -> 3.6 | E15: ='4_MCDA'!D31 -> 3.2875 | F15: Higher = better
B18: Sensitivity: C_out and C_in vs. Source–Receptor Distance (Alt B active)
B19: Distance (m) | C19: C_out baseline (µg/m³) | D19: C_in Baseline (µg/m³) | E19: C_in Alt A (µg/m³) | F19: C_in Alt B (µg/m³)
B20: 100 | C20: =('2_Model'!C6*1000000/(3.14159*156*(0.1^0.922)*108.2*(0.1^0.816)*'2_Model'!C5))*EXP(-('2_Model'!C7^2)/(2*(108.2*(0.1^0.816))^2)) -> 2837.9943 | D20: =('2_Model'!C6*1000000/(3.14159*156*(0.1^0.922)*108.2*(0.1^0.816)*'2_Model'!C5))*EXP(-('2_Model'!C7^2)/(2*(108.2*(0.1^0.816))^2))*('1_Inputs'!C25/('1_Inputs'!C25)) -> 2837.9943 | E20: =('2_Model'!C6*1000000/(3.14159*156*(0.1^0.922)*108.2*(0.1^0.816)*'2_Model'!C5))*EXP(-('2_Model'!C7^2)/(2*(108.2*(0.1^0.816))^2))*(1-'1_Inputs'!C19)*('1_Inputs'!C25/('1_Inputs'!C25)) -> 2128.4957 | F20: =('2_Model'!C6*1000000/(3.14159*156*(0.1^0.922)*108.2*(0.1^0.816)*'2_Model'!C5))*EXP(-('2_Model'!C7^2)/(2*(108.2*(0.1^0.816))^2))*('1_Inputs'!C25/('1_Inputs'!C25+'1_Inputs'!C26+('1_Inputs'!C25+'1_Inputs'!C26)*'1_Inputs'!C24)) -> 1150.5382
B21: 200 | C21: =('2_Model'!C6*1000000/(3.14159*156*(0.2^0.922)*108.2*(0.2^0.816)*'2_Model'!C5))*EXP(-('2_Model'!C7^2)/(2*(108.2*(0.2^0.816))^2)) -> 2596.5512 | D21: =('2_Model'!C6*1000000/(3.14159*156*(0.2^0.922)*108.2*(0.2^0.816)*'2_Model'!C5))*EXP(-('2_Model'!C7^2)/(2*(108.2*(0.2^0.816))^2))*('1_Inputs'!C25/('1_Inputs'!C25)) -> 2596.5512 | E21: =('2_Model'!C6*1000000/(3.14159*156*(0.2^0.922)*108.2*(0.2^0.816)*'2_Model'!C5))*EXP(-('2_Model'!C7^2)/(2*(108.2*(0.2^0.816))^2))*(1-'1_Inputs'!C19)*('1_Inputs'!C25/('1_Inputs'!C25)) -> 1947.4134 | F21: =('2_Model'!C6*1000000/(3.14159*156*(0.2^0.922)*108.2*(0.2^0.816)*'2_Model'!C5))*EXP(-('2_Model'!C7^2)/(2*(108.2*(0.2^0.816))^2))*('1_Inputs'!C25/('1_Inputs'!C25+'1_Inputs'!C26+('1_Inputs'!C25+'1_Inputs'!C26)*'1_Inputs'!C24)) -> 1052.6559
B22: 300 | C22: =('2_Model'!C6*1000000/(3.14159*156*(0.3^0.922)*108.2*(0.3^0.816)*'2_Model'!C5))*EXP(-('2_Model'!C7^2)/(2*(108.2*(0.3^0.816))^2)) -> 1659.8638 | D22: =('2_Model'!C6*1000000/(3.14159*156*(0.3^0.922)*108.2*(0.3^0.816)*'2_Model'!C5))*EXP(-('2_Model'!C7^2)/(2*(108.2*(0.3^0.816))^2))*('1_Inputs'!C25/('1_Inputs'!C25)) -> 1659.8638 | E22: =('2_Model'!C6*1000000/(3.14159*156*(0.3^0.922)*108.2*(0.3^0.816)*'2_Model'!C5))*EXP(-('2_Model'!C7^2)/(2*(108.2*(0.3^0.816))^2))*(1-'1_Inputs'!C19)*('1_Inputs'!C25/('1_Inputs'!C25)) -> 1244.8978 | F22: =('2_Model'!C6*1000000/(3.14159*156*(0.3^0.922)*108.2*(0.3^0.816)*'2_Model'!C5))*EXP(-('2_Model'!C7^2)/(2*(108.2*(0.3^0.816))^2))*('1_Inputs'!C25/('1_Inputs'!C25+'1_Inputs'!C26+('1_Inputs'!C25+'1_Inputs'!C26)*'1_Inputs'!C24)) -> 672.91775
B23: 500 | C23: =('2_Model'!C6*1000000/(3.14159*156*(0.5^0.922)*108.2*(0.5^0.816)*'2_Model'!C5))*EXP(-('2_Model'!C7^2)/(2*(108.2*(0.5^0.816))^2)) -> 797.72115 | D23: =('2_Model'!C6*1000000/(3.14159*156*(0.5^0.922)*108.2*(0.5^0.816)*'2_Model'!C5))*EXP(-('2_Model'!C7^2)/(2*(108.2*(0.5^0.816))^2))*('1_Inputs'!C25/('1_Inputs'!C25)) -> 797.72115 | E23: =('2_Model'!C6*1000000/(3.14159*156*(0.5^0.922)*108.2*(0.5^0.816)*'2_Model'!C5))*EXP(-('2_Model'!C7^2)/(2*(108.2*(0.5^0.816))^2))*(1-'1_Inputs'!C19)*('1_Inputs'!C25/('1_Inputs'!C25)) -> 598.29086 | F23: =('2_Model'!C6*1000000/(3.14159*156*(0.5^0.922)*108.2*(0.5^0.816)*'2_Model'!C5))*EXP(-('2_Model'!C7^2)/(2*(108.2*(0.5^0.816))^2))*('1_Inputs'!C25/('1_Inputs'!C25+'1_Inputs'!C26+('1_Inputs'!C25+'1_Inputs'!C26)*'1_Inputs'!C24)) -> 323.40046
B24: 750 | C24: =('2_Model'!C6*1000000/(3.14159*156*(0.75^0.922)*108.2*(0.75^0.816)*'2_Model'!C5))*EXP(-('2_Model'!C7^2)/(2*(108.2*(0.75^0.816))^2)) -> 417.6845 | D24: =('2_Model'!C6*1000000/(3.14159*156*(0.75^0.922)*108.2*(0.75^0.816)*'2_Model'!C5))*EXP(-('2_Model'!C7^2)/(2*(108.2*(0.75^0.816))^2))*('1_Inputs'!C25/('1_Inputs'!C25)) -> 417.6845 | E24: =('2_Model'!C6*1000000/(3.14159*156*(0.75^0.922)*108.2*(0.75^0.816)*'2_Model'!C5))*EXP(-('2_Model'!C7^2)/(2*(108.2*(0.75^0.816))^2))*(1-'1_Inputs'!C19)*('1_Inputs'!C25/('1_Inputs'!C25)) -> 313.26337 | F24: =('2_Model'!C6*1000000/(3.14159*156*(0.75^0.922)*108.2*(0.75^0.816)*'2_Model'!C5))*EXP(-('2_Model'!C7^2)/(2*(108.2*(0.75^0.816))^2))*('1_Inputs'!C25/('1_Inputs'!C25+'1_Inputs'!C26+('1_Inputs'!C25+'1_Inputs'!C26)*'1_Inputs'!C24)) -> 169.33155
B25: 1000 | C25: =('2_Model'!C6*1000000/(3.14159*156*(1^0.922)*108.2*(1^0.816)*'2_Model'!C5))*EXP(-('2_Model'!C7^2)/(2*(108.2*(1^0.816))^2)) -> 259.24315 | D25: =('2_Model'!C6*1000000/(3.14159*156*(1^0.922)*108.2*(1^0.816)*'2_Model'!C5))*EXP(-('2_Model'!C7^2)/(2*(108.2*(1^0.816))^2))*('1_Inputs'!C25/('1_Inputs'!C25)) -> 259.24315 | E25: =('2_Model'!C6*1000000/(3.14159*156*(1^0.922)*108.2*(1^0.816)*'2_Model'!C5))*EXP(-('2_Model'!C7^2)/(2*(108.2*(1^0.816))^2))*(1-'1_Inputs'!C19)*('1_Inputs'!C25/('1_Inputs'!C25)) -> 194.43236 | F25: =('2_Model'!C6*1000000/(3.14159*156*(1^0.922)*108.2*(1^0.816)*'2_Model'!C5))*EXP(-('2_Model'!C7^2)/(2*(108.2*(1^0.816))^2))*('1_Inputs'!C25/('1_Inputs'!C25+'1_Inputs'!C26+('1_Inputs'!C25+'1_Inputs'!C26)*'1_Inputs'!C24)) -> 105.09857
B26: 1500 | C26: =('2_Model'!C6*1000000/(3.14159*156*(1.5^0.922)*108.2*(1.5^0.816)*'2_Model'!C5))*EXP(-('2_Model'!C7^2)/(2*(108.2*(1.5^0.816))^2)) -> 130.53917 | D26: =('2_Model'!C6*1000000/(3.14159*156*(1.5^0.922)*108.2*(1.5^0.816)*'2_Model'!C5))*EXP(-('2_Model'!C7^2)/(2*(108.2*(1.5^0.816))^2))*('1_Inputs'!C25/('1_Inputs'!C25)) -> 130.53917 | E26: =('2_Model'!C6*1000000/(3.14159*156*(1.5^0.922)*108.2*(1.5^0.816)*'2_Model'!C5))*EXP(-('2_Model'!C7^2)/(2*(108.2*(1.5^0.816))^2))*(1-'1_Inputs'!C19)*('1_Inputs'!C25/('1_Inputs'!C25)) -> 97.904378 | F26: =('2_Model'!C6*1000000/(3.14159*156*(1.5^0.922)*108.2*(1.5^0.816)*'2_Model'!C5))*EXP(-('2_Model'!C7^2)/(2*(108.2*(1.5^0.816))^2))*('1_Inputs'!C25/('1_Inputs'!C25+'1_Inputs'!C26+('1_Inputs'!C25+'1_Inputs'!C26)*'1_Inputs'!C24)) -> 52.921285
B27: 2000 | C27: =('2_Model'!C6*1000000/(3.14159*156*(2^0.922)*108.2*(2^0.816)*'2_Model'!C5))*EXP(-('2_Model'!C7^2)/(2*(108.2*(2^0.816))^2)) -> 79.767232 | D27: =('2_Model'!C6*1000000/(3.14159*156*(2^0.922)*108.2*(2^0.816)*'2_Model'!C5))*EXP(-('2_Model'!C7^2)/(2*(108.2*(2^0.816))^2))*('1_Inputs'!C25/('1_Inputs'!C25)) -> 79.767232 | E27: =('2_Model'!C6*1000000/(3.14159*156*(2^0.922)*108.2*(2^0.816)*'2_Model'!C5))*EXP(-('2_Model'!C7^2)/(2*(108.2*(2^0.816))^2))*(1-'1_Inputs'!C19)*('1_Inputs'!C25/('1_Inputs'!C25)) -> 59.825424 | F27: =('2_Model'!C6*1000000/(3.14159*156*(2^0.922)*108.2*(2^0.816)*'2_Model'!C5))*EXP(-('2_Model'!C7^2)/(2*(108.2*(2^0.816))^2))*('1_Inputs'!C25/('1_Inputs'!C25+'1_Inputs'!C26+('1_Inputs'!C25+'1_Inputs'!C26)*'1_Inputs'!C24)) -> 32.338067

Sheet 4_MCDA
A1: Multi-Criteria Decision Analysis (MCDA) — Structured Comparison
A2: Score each alternative on a 1–5 scale (1=poor, 3=moderate, 5=excellent). Weights are set on the Inputs tab. Weighted score = weight × score. Blue cells are user-scored. An example pre-filled below shows how to interpret each criterion.
B3: Criterion (weight from Inputs) | C3: Score — Alt A | D3: Score — Alt B | E3: Scoring guidance
B4: 1. TECHNICAL EFFECTIVENESS (quantitative — pulled from model output)
B5: Outdoor concentration reduction (C_out reduction %) | C5: 3 | D5: 2 | E5: 5=≥40% reduction 4=30–40% 3=20–30% 2=10–20% 1=<10% [Alt A acts here]
B6: Indoor concentration reduction (C_in reduction %) | C6: 2 | D6: 5 | E6: 5=≥80% reduction 4=60–80% 3=40–60% 2=20–40% 1=<20% [Alt B acts here]
B7: Coverage of exposed population | C7: 4 | D7: 4 | E7: 5=all residents + outdoor workers 3=residents only 1=partial households
B8: Robustness across wind / weather conditions | C8: 3 | D8: 5 | E8: 5=works regardless of weather 3=moderate dependence 1=highly weather-dependent
B9: 2. COST & PRACTICALITY
B10: Upfront capital cost | C10: 3 | D10: 4 | E10: 5=very low (<$50k) 4=$50–200k 3=$200–500k 2=$500k–1M 1=>$1M
B11: Annual O&M burden | C11: 4 | D11: 3 | E11: 5=negligible 4=low (<$10k/yr) 3=moderate 2=high 1=very high
B12: Implementation timeline | C12: 2 | D12: 4 | E12: 5=<6 months 4=6–12 months 3=1–2 years 2=2–5 years 1=>5 years
B13: Dependency on resident/landlord action | C13: 5 | D13: 2 | E13: 5=no resident action needed 3=some cooperation 1=fully dependent on residents
B14: 3. PUBLIC HEALTH & SAFETY
B15: Benefit to most vulnerable residents (EJ focus) | C15: 4 | D15: 3 | E15: 5=strong benefit to lowest-income, highest-burden households 1=minimal or inequitable
B16: Protection of outdoor + transient populations | C16: 4 | D16: 1 | E16: 5=protects outdoor workers, children playing outside 1=only indoor occupants
B17: Secondary health risks from intervention | C17: 4 | D17: 3 | E17: 5=no secondary risks 3=minor risks (filter mold, inadequate ventilation) 1=significant
B18: Long-term health co-benefits | C18: 4 | D18: 3 | E18: 5=multiple co-benefits (noise, heat, mental health) 1=exposure reduction only
B19: 4. ENVIRONMENTAL CONSIDERATIONS
B20: Ecosystem co-benefits | C20: 5 | D20: 2 | E20: 5=strong (habitat, urban cooling, carbon) 3=neutral 1=negative
B21: Solid waste / material burden | C21: 4 | D21: 3 | E21: 5=no waste stream 3=minor (filter disposal) 1=significant material waste
B22: Energy consumption | C22: 5 | D22: 3 | E22: 5=no energy use 3=moderate (ERV fan) 1=high ongoing energy demand
B23: Pollutant shifting / unintended releases | C23: 4 | D23: 4 | E23: 5=no pollutant shifting 3=minor concerns 1=significant secondary pollution
B25: WEIGHTED MCDA SUMMARY
B26: Criterion | C26: Avg Score — Alt A | D26: Avg Score — Alt B
B27: Technical Effectiveness | C27: =AVERAGE(C5:C8) -> 3 | D27: =AVERAGE(D5:D8) -> 4 | E27: Weight: '1_Inputs'!C31
B28: Cost & Practicality | C28: =AVERAGE(C10:C13) -> 3.5 | D28: =AVERAGE(D10:D13) -> 3.25 | E28: Weight: '1_Inputs'!C32
B29: Public Health & Safety | C29: =AVERAGE(C15:C18) -> 4 | D29: =AVERAGE(D15:D18) -> 2.5 | E29: Weight: '1_Inputs'!C33
B30: Environmental | C30: =AVERAGE(C20:C23) -> 4.5 | D30: =AVERAGE(D20:D23) -> 3 | E30: Weight: '1_Inputs'!C34
B31: OVERALL WEIGHTED SCORE (max = 5.0) | C31: ='1_Inputs'!C31*C27+'1_Inputs'!C32*C28+'1_Inputs'!C33*C29+'1_Inputs'!C34*C30 -> 3.6 | D31: ='1_Inputs'!C31*D27+'1_Inputs'!C32*D28+'1_Inputs'!C33*D29+'1_Inputs'!C34*D30 -> 3.2875 | E31: Weighted sum of criterion averages × weights from Inputs tab
B33: INTERPRETATION: A score above 3.5 indicates a strong alternative. The higher-scoring alternative is preferred. If scores are within 0.2 of each other, consider a combined approach. Technical Effectiveness scores should be validated against model outputs on the 2_Model tab before finalizing the recommendation.

Sheet 5_Documentation
A1: Tool Documentation — AI Collaboration Record
B2: TOOL PURPOSE
B3: This tool implements a two-stage air quality model to compare engineering alternatives for reducing PM2.5 exposure experienced by residents of Commerce City, CO near the Suncor Refinery and Rawhide Energy Station. It quantifies outdoor pollutant concentrations using simplified Gaussian dispersion, translates those to indoor concentrations via a single-zone mass balance model, estimates daily occupant dose, and compares two interventions across four structured evaluation criteria using a weighted MCDA framework.
B4: INPUTS REQUIRED
B5: Emission rate (Q, g/s), stack height (m), wind speed (m/s), Pasquill-Gifford stability class (1–6), source-receptor distance (m), building infiltration rate (ACH), HEPA filter efficiency, mechanical ventilation rate, number of homes treated, per-home installation cost, annual O&M cost, vegetation buffer reduction factor, buffer capital cost, and MCDA criterion weights.
B6: MODELING APPROACH
B7: Outdoor concentrations use the Gaussian plume equation (centerline, ground-level) with Pasquill-Gifford dispersion coefficients (power-law form, stability class C as default). This is appropriate because the source is a point-source stack at a known height, distances are in the near-field (100–2000 m), and the goal is a comparative rather than regulatory-grade estimate. Indoor concentrations use the single-zone steady-state mass balance: C_in = C_out × ACH_nat / (ACH_nat + ACH_mech + removal rate), where removal rate = (ACH_nat + ACH_mech) × η_HEPA.
B8: OUTPUTS & COMPARISON STRUCTURE
B9: The tool produces: (1) outdoor C_out and indoor C_in concentrations for baseline and each alternative; (2) daily occupant dose in µg/day; (3) percent dose reduction vs. baseline; (4) capital and lifecycle costs; (5) a sensitivity table showing C_in across a range of distances (100–2000 m); (6) a concentration-vs-distance line chart; and (7) a weighted MCDA score across four criteria. Alternatives are evaluated under identical source and meteorological conditions to ensure comparability.
B10: INTERPRETING OUTPUTS
B11: A higher percent dose reduction means greater exposure benefit. The cost-per-percent-dose-reduction metric normalizes effectiveness against cost for direct comparison. On the MCDA tab, scores of 1–5 are assigned to each criterion sub-factor; the tool computes weighted averages using weights set on the Inputs tab. A weighted score >3.5 indicates a strong alternative; scores within 0.2 of each other suggest a combined approach may be warranted. The sensitivity chart helps identify at what distances each alternative provides meaningful benefit.
B12: AI COLLABORATION RECORD
B13: This tool was developed through substantial AI collaboration (Claude, Anthropic). The AI co-generated the Gaussian dispersion formula structure, single-zone indoor model equations, MCDA scoring rubric, sensitivity analysis table logic, and all Excel formula construction. The AI also assisted with: selecting appropriate P-G stability class coefficients, identifying the correct mass balance denominator for combined natural+mechanical+filtration ventilation, structuring the MCDA criterion weights, and debugging formula references across sheets. All modeling assumptions were reviewed and validated by the user.
... B17: Gaussian coefficients: Seinfeld & Pandis (2016), Atmospheric Chemistry and Physics. Indoor model: EPA Indoor Air Quality Tools for Schools (EPA 402-K-09-003). HEPA efficiency: ASHRAE Standard 52.2. Infiltration rates: ASHRAE Handbook of Fundamentals. Emission rates: EPA AP-42 / Colorado APEN database. P-G stability class guidance: EPA AERMOD Implementation Guide (EPA-454/B-19-027).
